gpype/__init__.py
gpype/__version__.py
gpype/__pyinstaller/__init__.py
gpype/__pyinstaller/hook-gpype.py
gpype/backend/__init__.py
gpype/backend/pipeline.py
gpype/backend/core/__init__.py
gpype/backend/core/i_node.py
gpype/backend/core/i_port.py
gpype/backend/core/io_node.py
gpype/backend/core/node.cp312-win_amd64.pyd
gpype/backend/core/o_node.py
gpype/backend/core/o_port.py
gpype/backend/filters/__init__.py
gpype/backend/filters/bandpass.py
gpype/backend/filters/bandstop.py
gpype/backend/filters/highpass.py
gpype/backend/filters/lowpass.py
gpype/backend/filters/moving_average.py
gpype/backend/filters/base/__init__.py
gpype/backend/filters/base/butterworth.py
gpype/backend/filters/base/generic_filter.py
gpype/backend/flow/__init__.py
gpype/backend/flow/framer.py
gpype/backend/flow/router.py
gpype/backend/flow/trigger.py
gpype/backend/sinks/__init__.py
gpype/backend/sinks/csv_writer.py
gpype/backend/sinks/lsl_sender.py
gpype/backend/sinks/udp_sender.py
gpype/backend/sinks/base/__init__.py
gpype/backend/sinks/base/file_writer.py
gpype/backend/sources/__init__.py
gpype/backend/sources/bci_core8.py
gpype/backend/sources/g_nautilus.py
gpype/backend/sources/generator.py
gpype/backend/sources/keyboard.py
gpype/backend/sources/udp_receiver.py
gpype/backend/sources/base/__init__.py
gpype/backend/sources/base/amplifier_source.py
gpype/backend/sources/base/event_source.py
gpype/backend/sources/base/fixed_rate_source.py
gpype/backend/sources/base/source.py
gpype/backend/timing/__init__.py
gpype/backend/timing/decimator.py
gpype/backend/timing/delay.py
gpype/backend/timing/hold.py
gpype/backend/transform/__init__.py
gpype/backend/transform/equation.py
gpype/backend/transform/fft.py
gpype/common/__init__.py
gpype/common/constants.py
gpype/common/settings.py
gpype/frontend/__init__.py
gpype/frontend/main_app.py
gpype/frontend/resources/gtec.ico
gpype/frontend/widgets/__init__.py
gpype/frontend/widgets/paradigm_presenter.py
gpype/frontend/widgets/performance_monitor.py
gpype-3.0.8.dist-info/licenses/LICENSE-GNCL.txt
gpype-3.0.8.dist-info/METADATA
gpype-3.0.8.dist-info/WHEEL
gpype-3.0.8.dist-info/entry_points.txt
gpype-3.0.8.dist-info/top_level.txt
gpype-3.0.8.dist-info/RECORD
